README.md
setup.py
pyspeeder/__init__.py
pyspeeder/browser.py
pyspeeder/config.py
pyspeeder/core.py
pyspeeder/helper.py
pyspeeder/proxy.py
pyspeeder.egg-info/PKG-INFO
pyspeeder.egg-info/SOURCES.txt
pyspeeder.egg-info/dependency_links.txt
pyspeeder.egg-info/top_level.txt