Metadata-Version: 2.1
Name: pyspeeder
Version: 0.0.9
Summary: Distribute web crawler based on redis.
Home-page: https://github.com/
Author: sumriser
Author-email: sumriser@163.com
License: UNKNOWN
Platform: UNKNOWN
Classifier: Programming Language :: Python :: 3
Classifier: License :: OSI Approved :: MIT License
Classifier: Operating System :: OS Independent
